{"trial_id": "18", "hyperparameters": {"space": [{"class_name": "Int", "config": {"name": "units_1", "default": null, "conditions": [], "min_value": 32, "max_value": 256, "step": 32, "sampling": "linear"}}, {"class_name": "Float", "config": {"name": "dropout_1", "default": 0.1, "conditions": [], "min_value": 0.1, "max_value": 0.5, "step": 0.1, "sampling": "linear"}}, {"class_name": "Boolean", "config": {"name": "use_second_layer", "default": false, "conditions": []}}, {"class_name": "Boolean", "config": {"name": "use_third_layer", "default": false, "conditions": []}}, {"class_name": "Boolean", "config": {"name": "use_batch_norm", "default": false, "conditions": []}}, {"class_name": "Choice", "config": {"name": "learning_rate", "default": 0.0001, "conditions": [], "values": [0.0001, 0.0005, 0.001, 0.005], "ordered": true}}, {"class_name": "Int", "config": {"name": "units_3", "default": null, "conditions": [], "min_value": 8, "max_value": 64, "step": 8, "sampling": "linear"}}, {"class_name": "Float", "config": {"name": "dropout_3", "default": 0.1, "conditions": [], "min_value": 0.1, "max_value": 0.3, "step": 0.1, "sampling": "linear"}}, {"class_name": "Int", "config": {"name": "units_2", "default": null, "conditions": [], "min_value": 16, "max_value": 128, "step": 16, "sampling": "linear"}}, {"class_name": "Float", "config": {"name": "dropout_2", "default": 0.1, "conditions": [], "min_value": 0.1, "max_value": 0.4, "step": 0.1, "sampling": "linear"}}], "values": {"units_1": 32, "dropout_1": 0.30000000000000004, "use_second_layer": true, "use_third_layer": true, "use_batch_norm": false, "learning_rate": 0.001, "units_3": 32, "dropout_3": 0.2, "units_2": 32, "dropout_2": 0.4}}, "metrics": {"metrics": {"accuracy": {"direction": "max", "observations": [{"value": [0.6278475522994995], "step": 53}]}, "f1_score": {"direction": "min", "observations": [{"value": [0.6321593821048737], "step": 53}]}, "loss": {"direction": "min", "observations": [{"value": [0.6456482112407684], "step": 53}]}, "precision": {"direction": "max", "observations": [{"value": [0.6250611245632172], "step": 53}]}, "recall": {"direction": "max", "observations": [{"value": [0.6394210457801819], "step": 53}]}, "val_accuracy": {"direction": "max", "observations": [{"value": [0.6165957450866699], "step": 53}]}, "val_f1_score": {"direction": "max", "observations": [{"value": [0.6543971300125122], "step": 53}]}, "val_loss": {"direction": "min", "observations": [{"value": [0.6559908986091614], "step": 53}]}, "val_precision": {"direction": "max", "observations": [{"value": [0.5948705971240997], "step": 53}]}, "val_recall": {"direction": "max", "observations": [{"value": [0.72742760181427], "step": 53}]}, "val_f1_sklearn": {"direction": "min", "observations": [{"value": [0.6543972003869805], "step": 53}]}}}, "score": 0.6543971300125122, "best_step": 53, "status": "COMPLETED", "message": null}